<categories>
  <category>
    <title>Fuzzy and Blue</title>
	<description>Can you tell the difference between a monster and a grouch?</description>
	<sound_id>12</sound_id>
	<url>http://java.ChaosLimited.com/ctwFuzzyBlue/xml</url>
  </category>
  <category>
    <title>___ is for Cookie</title>
	<description>What's your Muppet Quotient?</description>
	<sound_id>3</sound_id>
	<url>http://java.ChaosLimited.com/ctwCisFor/xml</url>
  </category>
  <category>
    <title>There goes the Neighborhood</title>
	<description>How much have you really learned from a television show?</description>
	<sound_id>6</sound_id>
	<url>http://java.ChaosLimited.com/ctwThereGoes/xml</url>
  </category>
  <category>
    <title>Another Broken Toaster</title>
	<description>Do you know the people in the neighborhood?</description>
	<sound_id>9</sound_id>
	<url>http://java.ChaosLimited.com/ctwAnotherBroken/xml</url>
  </category>
  <category>
    <title>Follow that Bird</title>
	<description>Where have you seen Sesame Street besides on Sesame Street?</description>
	<sound_id>13</sound_id>
	<url>http://java.ChaosLimited.com/ctwFollow/xml</url>
  </category>
  <category>
    <title>AB-CDEF..</title>
	<description>Can you sing, sing the songs?</description>
	<sound_id>8</sound_id>
	<url>http://java.ChaosLimited.com/ctwABC/xml</url>
  </category>
</categories>